zipcode_decoder_mcp/__init__.py
zipcode_decoder_mcp-0.1.3.dist-info/METADATA
zipcode_decoder_mcp-0.1.3.dist-info/WHEEL
zipcode_decoder_mcp-0.1.3.dist-info/entry_points.txt
zipcode_decoder_mcp-0.1.3.dist-info/RECORD
