Metadata-Version: 2.4
Name: zipcode-decoder-mcp
Version: 0.1.3
Summary: A Model Control Protocol (MCP) server that provides US zipcode lookup functionality. It can be used to decode zipcodes into city and state information.
Author: Yang
Requires-Python: >=3.13
Requires-Dist: mcp[cli]>=1.12.3
Requires-Dist: requests>=2.31.0
